setup.py
freebox/__init__.py
freebox/client.py
freebox/download.py
freebox/freebox.py
freebox.egg-info/PKG-INFO
freebox.egg-info/SOURCES.txt
freebox.egg-info/dependency_links.txt
freebox.egg-info/entry_points.txt
freebox.egg-info/requires.txt
freebox.egg-info/top_level.txt