Metadata-Version: 1.0
Name: freebox
Version: 0.1.2-dev
Summary: a freebox (French set-top box) python client and cli  management
Home-page: https://github.com/iXioN/python-freebox.git
Author: Antonin Lacombe
Author-email: antonin.lacombe@gmail.com
License: LGPLv3
Keywords: freebox
Platform: UNKNOWN
Classifier: Development Status :: 3 - Alpha
Classifier: License :: OSI Approved :: GNU Lesser General Public License v3 (LGPLv3)
Classifier: Natural Language :: English
Classifier: Environment :: Console
Classifier: Intended Audience :: Developers
Classifier: Operating System :: OS Independent
Classifier: Programming Language :: Python :: 2.6
Classifier: Programming Language :: Python :: 2.7
Classifier: Topic :: Software Development :: Libraries :: Python Modules
